{"version":2,"kind":"Article","sha256":"ade2f5e99e62467cd2c5382683e1fdb06ede6b897f1cdf21dbc6e8106d5ef671","slug":"index","location":"/zintro.md","dependencies":[],"frontmatter":{"title":"CSCI 210 Web Programming","content_includes_title":false,"authors":[{"nameParsed":{"literal":"James Goudy","given":"James","family":"Goudy"},"name":"James Goudy","id":"contributors-a_books\\csci210_webprog\\wpbookdocmov\\myst-generated-uid-0"}],"copyright":"2024 By James Goudy","exports":[{"format":"md","filename":"zintro.md","url":"/CSCI210/build/zintro-1611766f30811da90a7a1c7a38f6efbd.md"}]},"mdast":{"type":"root","children":[{"type":"block","children":[{"type":"paragraph","position":{"start":{"line":3,"column":1},"end":{"line":3,"column":1}},"children":[{"type":"text","value":"This is the course notes for CSCI 210 Web Programming.","position":{"start":{"line":3,"column":1},"end":{"line":3,"column":1}},"key":"jEhEXmVcup"}],"key":"IbpKNRFQWl"},{"type":"block","children":[{"type":"list","children":[{"type":"listItem","children":[{"type":"link","url":"/","internal":true,"children":[{"type":"text","value":"Web Programming","key":"fpBaZMUnPK"}],"urlSource":"/","key":"BgXRp6MiQg"}],"key":"DtcA8CfzUM"},{"type":"listItem","children":[{"type":"link","url":"/CSCI210/build/zphpintroduction-c7433a5a031c385f6ef13253bebb0e00.md","internal":true,"children":[{"type":"text","value":"PHP Introduction","key":"C9JWCBbqDq"}],"urlSource":"/zphpintroduction","static":true,"protocol":"file","key":"GRRfviYNEz"}],"key":"Wa3MYA75RS"},{"type":"listItem","children":[{"type":"link","url":"/CSCI210/build/zphpbasics-55b8463148594e6c8268f79baa0a2bbc.md","internal":true,"children":[{"type":"text","value":"PHP Basics","key":"BgFgsZ9kEa"}],"urlSource":"/zphpbasics","static":true,"protocol":"file","key":"B5qtTbASlG"}],"key":"mcUZLG140F"},{"type":"listItem","children":[{"type":"link","url":"/CSCI210/build/zloopif-993fceea5bffa5a50c57f84ab0b43263.md","internal":true,"children":[{"type":"text","value":"Loops and If","key":"w1x7mFzA93"}],"urlSource":"/zloopif","static":true,"protocol":"file","key":"BMJFEgylQk"}],"key":"M55z2qcPgE"},{"type":"listItem","children":[{"type":"link","url":"/zphparrays","internal":true,"children":[{"type":"text","value":"PHP Arrays","key":"ZuLcfaX6mY"}],"urlSource":"/zphparrays","dataUrl":"/zphparrays.json","protocol":"file","key":"yde8PpvJ4Z"}],"key":"dKV8acqInc"},{"type":"listItem","children":[{"type":"link","url":"/CSCI210/build/zfunctions-eb850969b3351f3a13757437ef74f5dd.md","internal":true,"children":[{"type":"text","value":"Functions","key":"dQ8MRTe1fZ"}],"urlSource":"/zfunctions","static":true,"protocol":"file","key":"zgeejmf4rq"}],"key":"mmJL8FiuLt"},{"type":"listItem","children":[{"type":"link","url":"/CSCI210/build/zfirstformspostandge-a8e1b3729a84466aa53f76e61af194df.md","internal":true,"children":[{"type":"text","value":"First Forms - POST and GET","key":"WDdQuM8QEK"}],"urlSource":"/zfirstformspostandget","static":true,"protocol":"file","key":"syJdpsE6qG"}],"key":"qqfDqK6Ric"},{"type":"listItem","children":[{"type":"link","url":"/CSCI210/build/zhtmlinputfieldrevie-0026b0ea036f25b57853ecc544a30bc1.md","internal":true,"children":[{"type":"text","value":"HTML Input Field Review","key":"biKWLpPJtv"}],"urlSource":"/zhtmlinputfieldreview","static":true,"protocol":"file","key":"loj00IPFST"}],"key":"QtlDWWR4ui"},{"type":"listItem","children":[{"type":"link","url":"/CSCI210/build/zsessionvariables-0b65163d27a2d5d5ecf6995b0885262c.md","internal":true,"children":[{"type":"text","value":"Session Variables","key":"lExIOj9MBa"}],"urlSource":"/zsessionvariables","static":true,"protocol":"file","key":"xXCsEzpM1p"},{"type":"list","children":[{"type":"listItem","children":[{"type":"link","url":"/CSCI210/build/zsessionhomeworkhint-e4ac8e9a0333e7073b8605545bbb662f.md","internal":true,"children":[{"type":"text","value":"Session Variable Homework Assignment Hint","key":"G9lKcZadk5"}],"urlSource":"/zsessionhomeworkhint","static":true,"protocol":"file","key":"XfcK8VMLB5"}],"key":"KivU3OVI7Y"}],"key":"xZmLR1TKeN"}],"key":"OExs2sDhFa"},{"type":"listItem","children":[{"type":"link","url":"/CSCI210/build/zpdoconnections-b11e5a3d4545865f428d3e7d36bea5a5.md","internal":true,"children":[{"type":"text","value":"PDO Connections","key":"SE2RX9BxXl"}],"urlSource":"/zpdoconnections","static":true,"protocol":"file","key":"GHvnlB81xX"}],"key":"yFBmFWCuI5"},{"type":"listItem","children":[{"type":"link","url":"/CSCI210/build/zphpclosingtags-95226f2d33b629d81e0e8fcbd3fc0104.md","internal":true,"children":[{"type":"text","value":"PHP Closing Tags: Leave Them Out Or Out","key":"fvDeMq2USx"}],"urlSource":"/zphpclosingtags","static":true,"protocol":"file","key":"xY7Q5Xl7fU"},{"type":"list","children":[{"type":"listItem","children":[{"type":"link","url":"/CSCI210/build/zpdofirstdatadbinser-b1f8230f1c5d5a354697e9424fc14449.md","internal":true,"children":[{"type":"text","value":"PDO - First Data Insert - Car Example","key":"ePpoV8frwi"}],"urlSource":"/zpdofirstdatadbinsertcarexample","static":true,"protocol":"file","key":"lFxFK4S96E"}],"key":"h1F98eAJao"},{"type":"listItem","children":[{"type":"link","url":"/CSCI210/build/zpdonoplaceholdersex-7e954a38a2631476c2e2bc4609f34a14.md","internal":true,"children":[{"type":"text","value":"PDO With No Named Placeholders","key":"SdSqw0PIg5"}],"urlSource":"/zpdonoplaceholdersexample","static":true,"protocol":"file","key":"InOlHSIvPf"}],"key":"oJIsKqWsRN"},{"type":"listItem","children":[{"type":"link","url":"/CSCI210/build/zstringsanitation-5a5d078fcf86738afdee89dfbf8f389f.md","internal":true,"children":[{"type":"text","value":"String Sanitation - filter_var()","key":"VdrTJGbQcE"}],"urlSource":"/zstringsanitation","static":true,"protocol":"file","key":"vtsYfybiJM"}],"key":"OFhm32ezAK"}],"key":"cLfdwIkpHe"}],"key":"ioEkttgR5b"},{"type":"listItem","children":[{"type":"link","url":"/CSCI210/build/zxssdefendingagainst-e3daab89cf044400c874c55bede2756b.md","internal":true,"children":[{"type":"text","value":"Defending Against Cross Site Scripting","key":"aWwNE7ygF1"}],"urlSource":"/zxssdefendingagainstxss","static":true,"protocol":"file","key":"qnNuoekxZY"},{"type":"list","children":[{"type":"listItem","children":[{"type":"link","url":"/CSCI210/build/zxssexamples-2d3564f8b7cb1bab357548d213e3aafa.md","internal":true,"children":[{"type":"text","value":"XSS Examples","key":"GIqQsfP7nw"}],"urlSource":"/zxssexamples","static":true,"protocol":"file","key":"JhS8vitVJH"}],"key":"NLXAEyPP5w"},{"type":"listItem","children":[{"type":"link","url":"/CSCI210/build/zxsscontentsecurityp-bcde0ffffc77deded237279ef157cfb8.md","internal":true,"children":[{"type":"text","value":"Content Security Policy","key":"VUBFNRFTfS"}],"urlSource":"/zxsscontentsecuritypolicy","static":true,"protocol":"file","key":"KuqLeDw9nE"}],"key":"XPy8rxRr1V"}],"key":"kd8etCsvxp"}],"key":"XhWdEuJteV"},{"type":"listItem","children":[{"type":"link","url":"/CSCI210/build/zpasswords-ede52edffc104e79219fb82ba49f6b53.md","internal":true,"children":[{"type":"text","value":"Passwords","key":"rplWEIuKyE"}],"urlSource":"/zpasswords","static":true,"protocol":"file","key":"MVBr33D5Ha"}],"key":"dbErb6XK4j"},{"type":"listItem","children":[{"type":"link","url":"/CSCI210/build/zaddeditdelete-7e7bb66653a112fca967180fbaa3d89b.md","internal":true,"children":[{"type":"text","value":"Add Edit Delete","key":"sGzH2Evspx"}],"urlSource":"/zaddeditdelete","static":true,"protocol":"file","key":"o6SfOWByNC"}],"key":"aZXoxdh2cx"},{"type":"listItem","children":[{"type":"link","url":"/CSCI210/build/zsavingpicturesindat-1ccc9709bb99975c80b10ab0d94079c5.md","internal":true,"children":[{"type":"text","value":"Saving Pictures In Database","key":"uurvhAe75k"}],"urlSource":"/zsavingpicturesindatabase","static":true,"protocol":"file","key":"kBNtrsUJA7"}],"key":"cwPcN52xOd"},{"type":"listItem","children":[{"type":"link","url":"/CSCI210/build/zreadingjson-7563bef390f0409770b7a7a24d225814.md","internal":true,"children":[{"type":"text","value":"Reading json","key":"iwCX0Tv2VE"}],"urlSource":"/zreadingjson","static":true,"protocol":"file","key":"FM7FkPh5Sa"}],"key":"HtXCapxa8E"},{"type":"listItem","children":[{"type":"link","url":"/CSCI210/build/zdatefunctionphp-2000edce36406946f618e8c2972d590f.md","internal":true,"children":[{"type":"text","value":"Date Function","key":"fFSPAxjiYo"}],"urlSource":"/zdatefunctionphp","static":true,"protocol":"file","key":"fcKuyKfJXv"}],"key":"aDkjp39JtO"},{"type":"listItem","children":[{"type":"link","url":"/CSCI210/build/zsqliteguide-41002ee9526409e6d47dfa668217e285.md","internal":true,"children":[{"type":"text","value":"PHP + SQLite Shortcut Guide","key":"j9S9AspqrC"}],"urlSource":"/zsqliteguide","static":true,"protocol":"file","key":"PH0AGdbITd"},{"type":"list","children":[{"type":"listItem","children":[{"type":"link","url":"/CSCI210/build/zsearchfiltersqlite-63e44f0758f0422707f55687fd11969e.md","internal":true,"children":[{"type":"text","value":"Search Filter - SQLITE","key":"K2pEtbn3Zj"}],"urlSource":"/zsearchfiltersqlite","static":true,"protocol":"file","key":"kKqSvLcgiP"}],"key":"XcvoEc6isa"}],"key":"oLUD9mOjoh"}],"key":"STgLBTOgVu"},{"type":"listItem","children":[{"type":"link","url":"/CSCI210/build/zyoutubedemo-bec7ab15f3c0b6d0998b190bbfafae55.md","internal":true,"children":[{"type":"text","value":"Z You Tube Demo","key":"kE9CnAs0dz"}],"urlSource":"/zyoutubedemo","static":true,"protocol":"file","key":"laRB6SqUOQ"}],"key":"zCdDrJErXF"}],"key":"SURfd50ieL"}],"data":{"part":"toc:project"},"key":"vj4dL0XGiw"}],"key":"wiQotidzAt"}],"key":"h5WbwttMph"},"references":{"cite":{"order":[],"data":{}}},"footer":{"navigation":{"next":{"title":"PHP Introduction","url":"/zphpintroduction","group":"Web Programming"}}},"domain":"http://localhost:3004"}